odoo8_addon_mail_footer_notified_partners-8.0.1.0.0.99.dev14-py2.7-nspkg.pth
odoo8_addon_mail_footer_notified_partners-8.0.1.0.0.99.dev14.dist-info/METADATA
odoo8_addon_mail_footer_notified_partners-8.0.1.0.0.99.dev14.dist-info/RECORD
odoo8_addon_mail_footer_notified_partners-8.0.1.0.0.99.dev14.dist-info/WHEEL
odoo8_addon_mail_footer_notified_partners-8.0.1.0.0.99.dev14.dist-info/namespace_packages.txt
odoo8_addon_mail_footer_notified_partners-8.0.1.0.0.99.dev14.dist-info/top_level.txt
odoo_addons/mail_footer_notified_partners/README.rst
odoo_addons/mail_footer_notified_partners/__init__.py
odoo_addons/mail_footer_notified_partners/__openerp__.py
odoo_addons/mail_footer_notified_partners/i18n/de.po
odoo_addons/mail_footer_notified_partners/i18n/el_GR.po
odoo_addons/mail_footer_notified_partners/i18n/es.po
odoo_addons/mail_footer_notified_partners/i18n/fi.po
odoo_addons/mail_footer_notified_partners/i18n/fr.po
odoo_addons/mail_footer_notified_partners/i18n/it.po
odoo_addons/mail_footer_notified_partners/i18n/mail_footer_notified_partners.pot
odoo_addons/mail_footer_notified_partners/i18n/sl.po
odoo_addons/mail_footer_notified_partners/models/__init__.py
odoo_addons/mail_footer_notified_partners/models/mail_followers.py
odoo_addons/mail_footer_notified_partners/static/description/icon.png
odoo_addons/mail_footer_notified_partners/tests/__init__.py
odoo_addons/mail_footer_notified_partners/tests/test_mail_notification.py
